huaweicloudsdkcodeartsartifact/__init__.py
huaweicloudsdkcodeartsartifact/v2/__init__.py
huaweicloudsdkcodeartsartifact/v2/codeartsartifact_async_client.py
huaweicloudsdkcodeartsartifact/v2/codeartsartifact_client.py
huaweicloudsdkcodeartsartifact/v2/model/__init__.py
huaweicloudsdkcodeartsartifact/v2/model/artifact_search_result.py
huaweicloudsdkcodeartsartifact/v2/model/attention_do.py
huaweicloudsdkcodeartsartifact/v2/model/audit_do.py
huaweicloudsdkcodeartsartifact/v2/model/audit_result.py
huaweicloudsdkcodeartsartifact/v2/model/base_pagination_response_entity.py
huaweicloudsdkcodeartsartifact/v2/model/base_pagination_response_entity_v5.py
huaweicloudsdkcodeartsartifact/v2/model/basic_dov5.py
huaweicloudsdkcodeartsartifact/v2/model/batch_delete_trashes_request.py
huaweicloudsdkcodeartsartifact/v2/model/batch_delete_trashes_response.py
huaweicloudsdkcodeartsartifact/v2/model/batch_restore_repo_request.py
huaweicloudsdkcodeartsartifact/v2/model/batch_restore_repo_response.py
huaweicloudsdkcodeartsartifact/v2/model/capacity_setting_vo.py
huaweicloudsdkcodeartsartifact/v2/model/create_artifactory_request.py
huaweicloudsdkcodeartsartifact/v2/model/create_artifactory_response.py
huaweicloudsdkcodeartsartifact/v2/model/create_artifactory_result.py
huaweicloudsdkcodeartsartifact/v2/model/create_attention_request.py
huaweicloudsdkcodeartsartifact/v2/model/create_attention_response.py
huaweicloudsdkcodeartsartifact/v2/model/create_docker_repositories_request.py
huaweicloudsdkcodeartsartifact/v2/model/create_docker_repositories_response.py
huaweicloudsdkcodeartsartifact/v2/model/create_docker_repository_do.py
huaweicloudsdkcodeartsartifact/v2/model/create_maven_repo_request.py
huaweicloudsdkcodeartsartifact/v2/model/create_maven_repo_response.py
huaweicloudsdkcodeartsartifact/v2/model/create_maven_repo_result.py
huaweicloudsdkcodeartsartifact/v2/model/create_not_maven_repo_do.py
huaweicloudsdkcodeartsartifact/v2/model/create_project_related_repository_request.py
huaweicloudsdkcodeartsartifact-3.1.184.dist-info/METADATA
huaweicloudsdkcodeartsartifact-3.1.184.dist-info/WHEEL
huaweicloudsdkcodeartsartifact-3.1.184.dist-info/licenses/LICENSE
huaweicloudsdkcodeartsartifact-3.1.184.dist-info/RECORD
